{

  "16916": {
    "ID": 16916,
    "Name": "Khorium Champion",
    "Aura": {
      "Effects": [
        {
          "EffectType": "GainProc",
          "ProcID": 14
        }
      ]
    }
  },

  "16915": {
    "ID": 28095,
    "Name": "Strength of the Champion",
    "Aura": {
      "Duration": 30000,
      "Effects": [
        {
          "EffectType": "GainStats",
          "Stats": [
            {
              "Stat": "Strength",
              "Value": 120.0
            }
          ]
        }
      ]
    }
  },

  "28092": {
    "ID": 28092,
    "Name": "Mongoose",
    "Aura": {
      "Effects": [
        {
          "EffectType": "GainProc",
          "ProcID": 5
        }
      ]
    }
  },

  "28093": {
    "ID": 28093,
    "Name": "Lightning Speed",
    "Aura": {
      "Duration": 15000,
      "Effects": [
        {
          "EffectType": "GainStats",
          "Stats": [
            {
              "Stat": "Agility",
              "Value": 120.0
            }
          ]
        },
        {
          "EffectType": "ModAttackSpeed",
          "Percent": 3
        }
      ]
    }
  },

  "34258": {
    "ID": 34258,
    "Name": "Justice",
    "Aura": {
      "Effects": [
        {
          "EffectType": "GainProc",
          "ProcID": 10
        }
      ]
    }
  },

  "34260": {
    "ID": 34260,
    "Name": "Justice",
    "Aura": {
      "Duration": 5000,
      "Effects": [
        {
          "EffectType": "GainStats",
          "Stats": [
            {
              "Stat": "CritRating",
              "Value": 53.0
            }
          ]
        }
      ]
    }
  },

  "34512": {
    "ID": 34513,
    "Name": "Lionheart",
    "Aura": {
      "Effects": [
        {
          "EffectType": "GainProc",
          "ProcID": 9
        }
      ]
    }
  },

  "34513": {
    "ID": 34512,
    "Name": "Lionheart",
    "Aura": {
      "Duration": 10000,
      "Effects": [
        {
          "EffectType": "GainStats",
          "Stats": [
            {
              "Stat": "Strength",
              "Value": 100.0
            }
          ]
        }
      ]
    }
  },

  "34579": {
    "ID": 34579,
    "Name": "Impale",
    "Target": "Enemy",
    "Effects": [
      {
        "EffectType": "Damage",
        "School": "Physical",
        "DefenseCategory": "None",
        "CritCategory": "Physical",
        "IgnoresDefenses": true,
        "OnCast": 0,
        "OnHit": 16,
        "OnCrit": 1,
        "MinEffect": 600,
        "MaxEffect": 600
      }
    ]
  },

  "34580": {
    "ID": 34580,
    "Name": "Despair",
    "Aura": {
      "Effects": [
        {
          "EffectType": "GainProc",
          "ProcID": 15
        }
      ]
    }
  },

  "34695": {
    "ID": 34695,
    "Name": "Drain Life",
    "Target": "Enemy",
    "Effects": [
      {
        "EffectType": "Damage",
        "School": "Shadow",
        "DefenseCategory": "Magic",
        "CritCategory": "None",
        "OnCast": 0,
        "OnHit": 512,
        "OnCrit": 0,
        "MinEffect": 285,
        "MaxEffect": 315
      }
    ]
  },

  "34696": {
    "ID": 34696,
    "Name": "Glaive of the Pit",
    "Aura": {
      "Effects": [
        {
          "EffectType": "GainProc",
          "ProcID": 16
        }
      ]
    }
  },

  "34774": {
    "ID": 34774,
    "Name": "Dragonspine Trophy",
    "Aura": {
      "Effects": [
        {
          "EffectType": "GainProc",
          "ProcID": 8
        }
      ]
    }
  },

  "34775": {
    "ID": 34775,
    "Name": "Dragonspine Trophy",
    "Aura": {
      "Duration": 10000,
      "Effects": [
        {
          "EffectType": "GainStats",
          "Stats": [
            {
              "Stat": "HasteRating",
              "Value": 325.0
            }
          ]
        },
        {
          "EffectType": "ModAttackSpeed",
          "Percent": 0
        }
      ]
    }
  },

  "35166": {
    "ID": 35166,
    "Name": "Lust for Battle",
    "Cooldown": 120000,
    "Aura": {
      "Duration": 20000,
      "Effects": [
        {
          "EffectType": "GainStats",
          "Stats": [
            {
              "Stat": "AttackPower",
              "Value": 278.0
            }
          ]
        }
      ]
    }
  },

  "36111": {
    "ID": 36111,
    "Name": "World Breaker",
    "Aura": {
      "Effects": [
        {
          "EffectType": "GainProc",
          "ProcID": 17
        }
      ]
    }
  },

  "36112": {
    "ID": 36112,
    "Name": "World Breaker",
    "Aura": {
      "Duration": 4000,
      "Effects": [
        {
          "EffectType": "GainStats",
          "Stats": [
            {
              "Stat": "CritRating",
              "Value": 900.09
            }
          ]
        },
        {
          "EffectType": "GainProc",
          "ProcID": 18
        }
      ]
    }
  },

  "36113": {
    "ID": 36113,
    "Name": "World Breaker Cancel",
    "Effects": [
      {
        "EffectType": "CancelAura",
        "MinEffect":  36112.0
      }
    ]
  },

  "36479": {
    "ID": 36479,
    "Name": "Devastation",
    "Aura": {
      "Effects": [
        {
          "EffectType": "GainProc",
          "ProcID": 12
        }
      ]
    }
  },

  "36470": {
    "ID": 36470,
    "Name": "Speed Infusion",
    "Aura": {
      "Duration": 30000,
      "Effects": [
        {
          "EffectType": "ModAttackSpeed",
          "Percent": 20
        }
      ]
    }
  },

  "37652": {
    "ID": 37652,
    "Name": "Demon Slaying 150",
    "Target": "Self",
    "Aura": {
      "Effects": [
        {
          "EffectType": "GainStatsCreature",
          "Stats": [
            {
              "Stat": "AttackPower",
              "Value": 150.0
            }
          ],
          "Creatures": [
            "Demon"
          ]
        }
      ]
    }
  },

  "38281": {
    "ID": 38282,
    "Name": "Singing Crystal Axe",
    "Aura": {
      "Effects": [
        {
          "EffectType": "GainProc",
          "ProcID": 13
        }
      ]
    }
  },

  "38282": {
    "ID": 38281,
    "Name": "The Blade\u0027s Song",
    "Aura": {
      "Duration": 10000,
      "Effects": [
        {
          "EffectType": "GainStats",
          "Stats": [
            {
              "Stat": "HasteRating",
              "Value": 400.0
            }
          ]
        },
        {
          "EffectType": "ModAttackSpeed",
          "Percent": 0
        }
      ]
    }
  },

  "39957": {
    "ID": 39957,
    "Name": "Increase Critical Damage 3%",
    "Aura": {
      "Effects": [
        {
          "EffectType": "ModStat",
          "Percent": 3,
          "Stats": [
            "CritDamage",
            "SpellCritDamage"
          ]
        }
      ]
    }
  },

  "429740": {
    "ID": 42975,
    "Name": "Executioner",
    "Aura": {
      "Effects": [
        {
          "EffectType": "GainProc",
          "ProcID": 6
        }
      ]
    }
  },

  "42976": {
    "ID": 42976,
    "Name": "Executioner",
    "Aura": {
      "Duration": 15000,
      "Effects": [
        {
          "EffectType": "GainStats",
          "Stats": [
            {
              "Stat": "ArmorPenetration",
              "Value": 840.0
            }
          ]
        }
      ]
    }
  },

  "46579": {
    "ID": 46579,
    "Name": "Deathfrost",
    "Effects": [
      {
        "EffectType": "Damage",
        "School": "Frost",
        "DefenseCategory": "Magic",
        "CritCategory": "Spell",
        "OnCast": 0,
        "OnHit": 0,
        "OnCrit": 1,
        "MinEffect": 150.0,
        "MaxEffect": 150.0
      }
    ]
  },

  "46662": {
    "ID": 46662,
    "Name": "Deathfrost",
    "Aura": {
      "Effects": [
        {
          "EffectType": "GainProc",
          "ProcID": 7
        }
      ]
    }
  }
}